lichenggong/__init__.py
lichenggong/Noodows/__bios__.py
lichenggong/Noodows/__init__.py
lichenggong/Noodows/__noodows__.py
lichenggong/Noodows/first.txt
lichenggong/Noodows/update.log
lichenggong/Noodows/version/build_version.txt
lichenggong/Noodows/version/version.txt
lichenggong/Program_Files/System/__calc__.py
lichenggong/Program_Files/System/__logo__.py
lichenggong/Program_Files/System/__n_explorer__.py
lichenggong/Program_Files/System/__thanks__.py
lichenggong/Program_Files/System/__user__.py
lichenggong-0.5.1.1.dist-info/METADATA
lichenggong-0.5.1.1.dist-info/WHEEL
lichenggong-0.5.1.1.dist-info/top_level.txt
lichenggong-0.5.1.1.dist-info/RECORD
