Metadata-Version: 2.1
Name: lichenggong
Version: 0.5.1.1
Summary: python 3   windows 10 (best)
Home-page: 
Classifier: Programming Language :: Python :: 3
Classifier: License :: OSI Approved :: MIT License
Classifier: Operating System :: OS Independent
Requires-Python: >=3
